iamex/__init__.py
iamex/async_client.py
iamex/client.py
iamex/compat.py
iamex/errors.py
iamex/image.py
iamex/vision.py
iamex-0.0.7.dist-info/licenses/LICENSE
iamex-0.0.7.dist-info/METADATA
iamex-0.0.7.dist-info/WHEEL
iamex-0.0.7.dist-info/top_level.txt
iamex-0.0.7.dist-info/RECORD
