Metadata-Version: 2.4
Name: iamex
Version: 0.0.7
Summary: Librería Python simple y poderosa para acceder a múltiples modelos de inteligencia artificial de forma unificada
Home-page: https://github.com/IA-Mexico/iamex
Author: Inteligencia Artificial México
Author-email: Inteligencia Artificial México <hostmaster@iamex.io>
Maintainer-email: Inteligencia Artificial México <hostmaster@iamex.io>
License: MIT
Project-URL: Homepage, https://github.com/IA-Mexico/iamex
Project-URL: Documentation, https://github.com/IA-Mexico/iamex#readme
Project-URL: Repository, https://github.com/IA-Mexico/iamex.git
Project-URL: Bug Tracker, https://github.com/IA-Mexico/iamex/issues
Project-URL: Source Code, https://github.com/IA-Mexico/iamex
Keywords: ai,machine learning,inference,models,iamex,artificial intelligence,chat,conversational ai,llm,nlp,python,api client
Classifier: Development Status :: 3 - Alpha
Classifier: Intended Audience :: Developers
Classifier: License :: OSI Approved :: MIT License
Classifier: Operating System :: OS Independent
Classifier: Programming Language :: Python :: 3
Classifier: Programming Language :: Python :: 3.7
Classifier: Programming Language :: Python :: 3.8
Classifier: Programming Language :: Python :: 3.9
Classifier: Programming Language :: Python :: 3.10
Classifier: Programming Language :: Python :: 3.11
Classifier: Topic :: Software Development :: Libraries :: Python Modules
Classifier: Topic :: Scientific/Engineering :: Artificial Intelligence
Requires-Python: >=3.7
License-File: LICENSE
Requires-Dist: requests>=2.25.0
Provides-Extra: dev
Requires-Dist: pytest>=6.0; extra == "dev"
Requires-Dist: pytest-cov>=2.0; extra == "dev"
Requires-Dist: black>=21.0; extra == "dev"
Requires-Dist: flake8>=3.8; extra == "dev"
Requires-Dist: mypy>=0.800; extra == "dev"
Dynamic: author
Dynamic: home-page
Dynamic: license-file
Dynamic: requires-python
